typarse/__about__.py
typarse/__init__.py
typarse/config.py
typarse/parsing.py
typarse-4.2.0.dist-info/METADATA
typarse-4.2.0.dist-info/WHEEL
typarse-4.2.0.dist-info/licenses/LICENSE.txt
typarse-4.2.0.dist-info/RECORD
