Metadata-Version: 2.3
Name: typarse
Version: 4.2.0
Summary: Simple type-based argument parsing
Project-URL: Documentation, https://github.com/RedTachyon/typarse#readme
Project-URL: Issues, https://github.com/RedTachyon/typarse/issues
Project-URL: Source, https://github.com/RedTachyon/typarse
Author-email: RedTachyon <ariel.j.kwiatkowski@gmail.com>
License-Expression: GPL-3.0
License-File: LICENSE.txt
Classifier: Development Status :: 4 - Beta
Classifier: Programming Language :: Python
Classifier: Programming Language :: Python :: 3.8
Classifier: Programming Language :: Python :: 3.9
Classifier: Programming Language :: Python :: 3.10
Classifier: Programming Language :: Python :: 3.11
Classifier: Programming Language :: Python :: 3.12
Classifier: Programming Language :: Python :: Implementation :: CPython
Classifier: Programming Language :: Python :: Implementation :: PyPy
Requires-Python: >=3.8
